baka.py
bakabakabaka-0.10.5.dist-info/licenses/LICENSE
bakabakabaka-0.10.5.dist-info/METADATA
bakabakabaka-0.10.5.dist-info/WHEEL
bakabakabaka-0.10.5.dist-info/entry_points.txt
bakabakabaka-0.10.5.dist-info/top_level.txt
bakabakabaka-0.10.5.dist-info/RECORD
