Metadata-Version: 2.4
Name: bakabakabaka
Version: 0.10.5
Summary: the stupid configuration tracker using the stupid content tracker
License-Expression: GPL-3.0-or-later
Project-URL: Homepage, https://github.com/elesiuta/baka
License-File: LICENSE
Requires-Dist: argcomplete
Dynamic: license-file
